jupyter_sidebar
