Metadata-Version: 1.1
Name: jupyter-sidebar
Version: 0.1.1
Summary: Sidebar extension for Jupyter
Home-page: https://github.com/gywn/jupyter_sidebar
Author: UNKNOWN
Author-email: UNKNOWN
License: UNKNOWN
Download-URL: https://github.com/gywn/jupyter_sidebar/archive/0.1.1.tar.gz
Platform: UNKNOWN
